hsmk/__init__.py
hsmk/cmds/__init__.py
hsmk/cmds/hsm_dump_sb.py
hsmk/cmds/hsm_dump_us.py
hsmk/cmds/hsm_test_spend.py
hsmk/cmds/hsmgen.py
hsmk/cmds/hsmk.py
hsmk/cmds/hsmmerge.py
hsmk/cmds/hsmpk.py
hsmk/cmds/hsmwizard.py
hsmk/cmds/poser_gen.py
hsmk/cmds/poser_verify.py
hsmk/cmds/qrint.py
hsmk/consensus/__init__.py
hsmk/consensus/conditions.py
hsmk/core/__init__.py
hsmk/core/signing_hints.py
hsmk/core/unsigned_spend.py
hsmk/debug/__init__.py
hsmk/debug/debug_spend_bundle.py
hsmk/klvm/__init__.py
hsmk/klvm/disasm.py
hsmk/klvm_serde/__init__.py
hsmk/process/__init__.py
hsmk/process/sign.py
hsmk/puzzles/conlang.py
hsmk/puzzles/p2_conditions.py
hsmk/puzzles/p2_delegated_puzzle_or_hidden_puzzle.py
hsmk/util/__init__.py
hsmk/util/byte_chunks.py
hsmk/util/qrint_encoding.py
hsmk/util/type_tree.py
hsmk-0.3.2.dist-info/LICENSE
hsmk-0.3.2.dist-info/METADATA
hsmk-0.3.2.dist-info/WHEEL
hsmk-0.3.2.dist-info/entry_points.txt
hsmk-0.3.2.dist-info/top_level.txt
hsmk-0.3.2.dist-info/RECORD
