Metadata-Version: 2.1
Name: hsmk
Version: 0.3.2
Summary: Hardware security module simulator for chik bls12_381 signatures
Author-email: Richard Kiss <him@richardkiss.com>
License: Apache License
License-File: LICENSE
Requires-Dist: segno ==1.4.1
Requires-Dist: chik-base >=0.1.5
Requires-Dist: chiklisp-puzzles >=0.1.1
Provides-Extra: dev
Requires-Dist: flake8 >=4.0.1 ; extra == 'dev'
Requires-Dist: black >=22.6 ; extra == 'dev'
Requires-Dist: pytest ; extra == 'dev'
